shapeshift_cli/__init__.py
shapeshift_cli/__main__.py
shapeshift_cli/shapeshift_cli.py
shapeshift_cli-1.0.1.dist-info/DESCRIPTION.rst
shapeshift_cli-1.0.1.dist-info/METADATA
shapeshift_cli-1.0.1.dist-info/RECORD
shapeshift_cli-1.0.1.dist-info/WHEEL
shapeshift_cli-1.0.1.dist-info/entry_points.txt
shapeshift_cli-1.0.1.dist-info/metadata.json
shapeshift_cli-1.0.1.dist-info/top_level.txt
